napari_plugin_devtools/__init__.py
napari_plugin_devtools/__main__.py
napari_plugin_devtools/_version.py
napari_plugin_devtools/plugin_tester.py
napari_plugin_devtools/validation.py
napari_plugin_devtools-0.4.2.dist-info/LICENSE
napari_plugin_devtools-0.4.2.dist-info/METADATA
napari_plugin_devtools-0.4.2.dist-info/WHEEL
napari_plugin_devtools-0.4.2.dist-info/entry_points.txt
napari_plugin_devtools-0.4.2.dist-info/top_level.txt
napari_plugin_devtools-0.4.2.dist-info/RECORD
